plotly3d/__init__.py
plotly3d/plot.py
plotly3d-0.4.12.dist-info/LICENSE
plotly3d-0.4.12.dist-info/METADATA
plotly3d-0.4.12.dist-info/WHEEL
plotly3d-0.4.12.dist-info/top_level.txt
plotly3d-0.4.12.dist-info/RECORD
