Metadata-Version: 2.1
Name: plotly3d
Version: 0.4.12
Summary: A helper for ploting scatter plots and trajectory plots with plotly
Home-page: https://github.com/xingzhis/plotly3d
Author: Xingzhi Sun
Author-email: xingzhi.sun@yale.edu
License: MIT
Keywords: plotly,plotly 3d,3d plotting,3d scatter,3d trajectory
License-File: LICENSE
Requires-Dist: plotly
Requires-Dist: scikit-learn
Requires-Dist: pandas
Requires-Dist: numpy
